Metadata-Version: 2.1
Name: thematch-2.1
Version: 2.1
Summary: thematch_2.1
Home-page: https://github.com/ExpertOfAI/thematch
Author: ExpertOfAI1
License: MIT
Classifier: Programming Language :: Python :: 3
Classifier: License :: OSI Approved :: MIT License
Classifier: Operating System :: OS Independent
Requires-Python: >=3.6
